MANIFEST.in
README.rst
setup.py
webassets_closure_soy.egg-info/PKG-INFO
webassets_closure_soy.egg-info/SOURCES.txt
webassets_closure_soy.egg-info/dependency_links.txt
webassets_closure_soy.egg-info/requires.txt
webassets_closure_soy.egg-info/top_level.txt
webassets_ext/__init__.py