Metadata-Version: 1.1
Name: webassets-closure-soy
Version: 1.0.0
Summary: Integration of Google's Soy Template Compiler with the webassets package.
Home-page: https://pypi.python.org/pypi/webassets-closure-soy/
Author: Michael Su
Author-email: mdasu1@gmail.com
License: BSD
Platform: UNKNOWN
Classifier: Development Status :: 5 - Production/Stable
Classifier: Environment :: Web Environment
Classifier: License :: OSI Approved :: BSD License
Classifier: Topic :: Internet :: WWW/HTTP :: Site Management
